AcpHub.py
__init__.py
acp_idl.py
enumdef.py
notify.py
pyacp.py
read.py
read_state.py
readwrite.py
resettime.py
write.py
write_ctrl.py
acp_libs/lib/__init__.py
acp_libs/lib/linux/__init__ .py
acp_libs/lib/linux/libacp-c.so
acp_libs/lib/linux/libacp-core.so
acp_libs/lib/win/__init__.py
acp_libs/lib/win/acp-c.dll
acp_libs/lib/win/acp-core.dll
pyacp-0.2.2.dist-info/METADATA
pyacp-0.2.2.dist-info/WHEEL
pyacp-0.2.2.dist-info/top_level.txt
pyacp-0.2.2.dist-info/RECORD
